mathinspector/__init__.py
mathinspector/__main__.py
mathinspector/_dist_version.py
mathinspector/animation.py
mathinspector/config.py
mathinspector/examples.py
mathinspector/mainmenu.py
mathinspector/modules.py
mathinspector/objects.py
mathinspector/project.py
mathinspector/assets/ABOUT.md
mathinspector/assets/LICENSE
mathinspector/assets/icons_3.icns
mathinspector/assets/logo.xcf
mathinspector/assets/logo_2.ico
mathinspector/assets/logo_2.png
mathinspector/assets/img/blank-file.png
mathinspector/assets/img/console-hover.png
mathinspector/assets/img/console-selected-alt.png
mathinspector/assets/img/console-selected.png
mathinspector/assets/img/console.png
mathinspector/assets/img/docviewer-hover.png
mathinspector/assets/img/docviewer-icon.png
mathinspector/assets/img/docviewer-selected-alt.png
mathinspector/assets/img/docviewer-selected.png
mathinspector/assets/img/docviewer.png
mathinspector/assets/img/fa-edit-hover.png
mathinspector/assets/img/fa-edit-selected-alt.png
mathinspector/assets/img/fa-edit-selected.png
mathinspector/assets/img/fa-edit.png
mathinspector/assets/img/fa-python.png
mathinspector/assets/img/folder-open.png
mathinspector/assets/img/folder.png
mathinspector/assets/img/function-f.png
mathinspector/assets/img/markdown.png
mathinspector/assets/img/mathinspector.png
mathinspector/assets/img/node-active.png
mathinspector/assets/img/node-connect.png
mathinspector/assets/img/node.png
mathinspector/assets/img/output-hover.png
mathinspector/assets/img/output-icon.png
mathinspector/assets/img/output-selected-alt.png
mathinspector/assets/img/output-selected.png
mathinspector/assets/img/output.png
mathinspector/assets/img/python-alt.png
mathinspector/assets/img/pythonlogo-color-2.png
mathinspector/assets/img/pythonlogo-color.png
mathinspector/assets/img/pythonlogo-disabled.png
mathinspector/assets/img/test-icon.png
mathinspector/assets/img/workspace-hover.png
mathinspector/assets/img/workspace-selected-alt.png
mathinspector-0.9.4.dist-info/LICENSE
mathinspector-0.9.4.dist-info/METADATA
mathinspector-0.9.4.dist-info/WHEEL
mathinspector-0.9.4.dist-info/entry_points.txt
mathinspector-0.9.4.dist-info/top_level.txt
mathinspector-0.9.4.dist-info/RECORD
