Metadata-Version: 2.1
Name: mathinspector
Version: 0.9.4
Summary: A visual programing environment for scientific computing with Python
Home-page: https://mathinspector.com
Author: Matt Calhoun
Maintainer: Casper da Costa-Luis
Maintainer-email: casper.dcl@physics.org
License: GPL 3.0+
Project-URL: Repository, https://github.com/MathInspector/MathInspector
Project-URL: Changelog, https://github.com/MathInspector/MathInspector/releases
Keywords: python,animation,mathinspector,math
Platform: any
Classifier: Development Status :: 4 - Beta
Classifier: Environment :: Console
Classifier: Environment :: GPU
Classifier: Intended Audience :: Developers
Classifier: Intended Audience :: Education
Classifier: Intended Audience :: End Users/Desktop
Classifier: Intended Audience :: Science/Research
Classifier: License :: OSI Approved :: GNU General Public License v3 or later (GPLv3+)
Classifier: Operating System :: MacOS
Classifier: Operating System :: Microsoft
Classifier: Operating System :: OS Independent
Classifier: Operating System :: POSIX
Classifier: Operating System :: Unix
Classifier: Programming Language :: Python :: 3
Classifier: Programming Language :: Python :: 3.6
Classifier: Programming Language :: Python :: 3.7
Classifier: Programming Language :: Python :: 3.8
Classifier: Programming Language :: Python :: 3 :: Only
Classifier: Topic :: Artistic Software
Classifier: Topic :: Documentation
Classifier: Topic :: Education
Classifier: Topic :: Games/Entertainment :: Simulation
Classifier: Topic :: Multimedia :: Graphics
Classifier: Topic :: Scientific/Engineering :: Visualization
Classifier: Topic :: Software Development :: Code Generators
Classifier: Topic :: Software Development :: Debuggers
Classifier: Topic :: Software Development :: Interpreters
Classifier: Topic :: Software Development :: Libraries
Classifier: Topic :: Software Development :: Libraries :: pygame
Classifier: Topic :: Software Development :: Libraries :: Python Modules
Classifier: Topic :: Software Development :: User Interfaces
Classifier: Topic :: Text Editors :: Integrated Development Environments (IDE)
Classifier: Topic :: Text Processing :: Markup
Provides: mathinspector
Requires-Python: >=3.6
Requires-Dist: cloudpickle
Requires-Dist: numpy
Requires-Dist: pillow
Requires-Dist: pygame
Requires-Dist: pyglm
Requires-Dist: PyOpenGL
Requires-Dist: PyOpenGL-accelerate
Requires-Dist: setuptools
Requires-Dist: scikit-image
Requires-Dist: scipy
Requires-Dist: ttkthemes
Requires-Dist: watchdog
